{
    "id": "RC2d4655fa1d984fdf8a08fceb18c98ad0",
    "type": "rule_components",
    "attributes": {
        "created_at": "2022-11-29T16:31:21.385Z",
        "delegate_descriptor_id": "core::actions::custom-code",
        "deleted_at": null,
        "dirty": false,
        "name": "Tag: googleAnalytics_eventCommunityProfileSignup",
        "negate": false,
        "order": 0,
        "rule_order": 50,
        "timeout": 2000,
        "delay_next": true,
        "published": true,
        "published_at": null,
        "revision_number": 0,
        "updated_at": "2023-03-02T16:15:34.788Z",
        "created_by_email": "gustavo.rodriguez@sephora.com",
        "created_by_display_name": "Gustavo Rodriguez",
        "updated_by_email": "rachel.joss@sephora.com",
        "updated_by_display_name": "rachel joss",
        "settings": "{\"source\":\"/* \\n\\n// This code is commented on the migration process as it was marked as high risk because of the use of eval()\\n\\nfunction isCookiePresent(name) {\\n  var match = document.cookie.match(new RegExp('(^| )' + name + '=([^;]+)'));\\n  var result;\\n  if (match) {\\n    var cookieValue = match[0].split(\\\"=\\\")[1];\\n    result = eval(cookieValue);\\n  }\\n  else{\\n    result = false;\\n  }\\n  return result;\\n}\\n\\n// if (isCookiePresent('cpCreateSuccess') \\u0026\\u0026 !isCookiePresent('cpCreateTagFired')) {\\n  \\n  // This is there the gtag() call was placed. \\n  \\n  // document.cookie = \\\"cpCreateTagFired=true; path=/;\\\";\\n// }\\n*/\\nvar gaId = _satellite.getVar('[TMS] UA Property Id');\\ngtag('event', 'signup', {\\n    'send_to': gaId,\\n    'event_category': 'User Engagement',\\n    'event_label': 'Community Profile Creation',\\n    'value': digitalData.user[0].segment.biAccountId // _satellite.getVar('[TMS] BI Account Number - asyncPageLoad')\\n});\",\"language\":\"javascript\"}"
    },
    "relationships": {
        "updated_with_extension_package": {
            "links": {
                "related": "https://reactor.adobe.io/rule_components/RC2d4655fa1d984fdf8a08fceb18c98ad0/updated_with_extension_package"
            },
            "data": {
                "id": "EPd22815afd48447aa955be6a3a012e3b5",
                "type": "extension_packages"
            }
        },
        "updated_with_extension": {
            "links": {
                "related": "https://reactor.adobe.io/rule_components/RC2d4655fa1d984fdf8a08fceb18c98ad0/updated_with_extension"
            },
            "data": {
                "id": "EX06a7afc619ae4214a074cb5399abf9fa",
                "type": "extensions"
            }
        },
        "extension": {
            "links": {
                "related": "https://reactor.adobe.io/rule_components/RC2d4655fa1d984fdf8a08fceb18c98ad0/extension"
            },
            "data": {
                "id": "EX881e591abc3d4b29b9681e2a4d337f74",
                "type": "extensions"
            }
        },
        "notes": {
            "links": {
                "related": "https://reactor.adobe.io/rule_components/RC2d4655fa1d984fdf8a08fceb18c98ad0/notes"
            }
        },
        "origin": {
            "links": {
                "related": "https://reactor.adobe.io/rule_components/RC2d4655fa1d984fdf8a08fceb18c98ad0/origin"
            },
            "data": {
                "id": "RC2d4655fa1d984fdf8a08fceb18c98ad0",
                "type": "rule_components"
            }
        },
        "property": {
            "links": {
                "related": "https://reactor.adobe.io/properties/PR28bc45fcba184e70b64b2f0cf7fe70f8"
            },
            "data": {
                "id": "PR28bc45fcba184e70b64b2f0cf7fe70f8",
                "type": "properties"
            }
        },
        "rules": {
            "links": {
                "related": "https://reactor.adobe.io/rule_components/RC2d4655fa1d984fdf8a08fceb18c98ad0/rules"
            }
        }
    },
    "links": {
        "extension": "https://reactor.adobe.io/extensions/EX881e591abc3d4b29b9681e2a4d337f74",
        "origin": "https://reactor.adobe.io/rule_components/RC2d4655fa1d984fdf8a08fceb18c98ad0",
        "rules": "https://reactor.adobe.io/rule_components/RC2d4655fa1d984fdf8a08fceb18c98ad0/rules",
        "self": "https://reactor.adobe.io/rule_components/RC2d4655fa1d984fdf8a08fceb18c98ad0"
    },
    "meta": {
        "latest_revision_number": 7
    }
}
